[
  {
    "source": "antler",
    "name": "Lodgicl",
    "description": "Lodgicl",
    "logo": "https://cdn.prod.website-files.com/68d622fc073c7e5dead1105e/695ee252e11af0cdba1f3264_portfolio%252Fcompany%252F5570fc55-aa97-4739-b48a-7b1776c39368%252F1742604248442-Lodgicl.avif",
    "website": "https://www.lodgicl.com/",
    "location": "We’re connecting insurers and their suppliers through structured data and intelligent workflows.",
    "region": "",
    "subregion": "",
    "tags": [
      "Australia\nFinTech\n2024",
      "Australia",
      "FinTech",
      "2024"
    ],
    "year": "",
    "program": "Antler",
    "programSlugs": [
      "antler"
    ],
    "isExit": false,
    "isUnicorn": false,
    "isBCorp": false,
    "isCurrentSession": false,
    "social": {
      "linkedin": "",
      "twitter": "",
      "facebook": "",
      "crunchbase": ""
    },
    "extra": {}
  }
]