[
  {
    "source": "yc",
    "name": "Matterport",
    "description": "Turn physical objects and environments into 3D models in seconds.",
    "logo": "https://bookface-images.s3.amazonaws.com/small_logos/b271a79c3b59d6344c90e2803525a22f2a5e8406.png",
    "website": "http://matterport.com",
    "location": "Sunnyvale, CA, USA",
    "region": "United States of America",
    "subregion": "",
    "tags": [
      "Consumer",
      "Virtual and Augmented Reality",
      "Computer Vision"
    ],
    "year": 2012,
    "program": "YC Winter 2012",
    "programSlugs": [
      "yc-winter-2012"
    ],
    "isExit": true,
    "isUnicorn": false,
    "isBCorp": false,
    "isCurrentSession": false,
    "social": {
      "linkedin": "",
      "twitter": "",
      "facebook": "",
      "crunchbase": ""
    },
    "extra": {}
  },
  {
    "source": "yc",
    "name": "Flutter",
    "description": "Flutter combined computer vision technology with the built-in webcams…",
    "logo": "/company/thumb/missing.png",
    "website": "http://flutterapp.com",
    "location": "Santa Monica, CA, USA",
    "region": "United States of America",
    "subregion": "",
    "tags": [
      "Engineering, Product and Design",
      "Computer Vision"
    ],
    "year": 2012,
    "program": "YC Winter 2012",
    "programSlugs": [
      "yc-winter-2012"
    ],
    "isExit": true,
    "isUnicorn": false,
    "isBCorp": false,
    "isCurrentSession": false,
    "social": {
      "linkedin": "",
      "twitter": "",
      "facebook": "",
      "crunchbase": ""
    },
    "extra": {}
  },
  {
    "source": "yc",
    "name": "SimplyListed",
    "description": "Sell your stuff.",
    "logo": "/company/thumb/missing.png",
    "website": "http://simplylisted.com",
    "location": "New York City, NY, USA; San Francisco, CA, USA",
    "region": "United States of America",
    "subregion": "",
    "tags": [
      "Consumer",
      "Home and Personal",
      "Marketplace",
      "Computer Vision"
    ],
    "year": 2011,
    "program": "YC Winter 2011",
    "programSlugs": [
      "yc-winter-2011"
    ],
    "isExit": false,
    "isUnicorn": false,
    "isBCorp": false,
    "isCurrentSession": false,
    "social": {
      "linkedin": "",
      "twitter": "",
      "facebook": "",
      "crunchbase": ""
    },
    "extra": {}
  },
  {
    "source": "yc",
    "name": "GazeHawk",
    "description": "Eyetracking using webcams.",
    "logo": "https://bookface-images.s3.amazonaws.com/small_logos/7b6bb6a40cbe23dd398442068cb5d69e8e784f57.png",
    "website": "http://gazehawk.com",
    "location": "Mountain View, CA, USA",
    "region": "United States of America",
    "subregion": "",
    "tags": [
      "Engineering, Product and Design",
      "Computer Vision"
    ],
    "year": 2010,
    "program": "YC Summer 2010",
    "programSlugs": [
      "yc-summer-2010"
    ],
    "isExit": true,
    "isUnicorn": false,
    "isBCorp": false,
    "isCurrentSession": false,
    "social": {
      "linkedin": "",
      "twitter": "",
      "facebook": "",
      "crunchbase": ""
    },
    "extra": {}
  },
  {
    "source": "yc",
    "name": "VizeraLabs",
    "description": "Augmented reality through projectors",
    "logo": "/company/thumb/missing.png",
    "website": "http://vizeralabs.com",
    "location": "Sunnyvale, CA, USA",
    "region": "United States of America",
    "subregion": "",
    "tags": [
      "Retail",
      "Augmented Reality",
      "Computer Vision"
    ],
    "year": 2014,
    "program": "YC Summer 2014",
    "programSlugs": [
      "yc-summer-2014"
    ],
    "isExit": false,
    "isUnicorn": false,
    "isBCorp": false,
    "isCurrentSession": false,
    "social": {
      "linkedin": "",
      "twitter": "",
      "facebook": "",
      "crunchbase": ""
    },
    "extra": {}
  },
  {
    "source": "yc",
    "name": "Dabble",
    "description": "A synthetic photo studio for e-commerce",
    "logo": "https://bookface-images.s3.amazonaws.com/small_logos/ded86f0a0f49180c787803bef08563dd167f5851.png",
    "website": "https://dabble.so",
    "location": "Toronto, ON, Canada; Remote",
    "region": "Canada",
    "subregion": "",
    "tags": [
      "Marketing",
      "Artificial Intelligence",
      "Augmented Reality",
      "Computer Vision"
    ],
    "year": 2015,
    "program": "YC Winter 2015",
    "programSlugs": [
      "yc-winter-2015"
    ],
    "isExit": false,
    "isUnicorn": false,
    "isBCorp": false,
    "isCurrentSession": false,
    "social": {
      "linkedin": "",
      "twitter": "",
      "facebook": "",
      "crunchbase": ""
    },
    "extra": {}
  },
  {
    "source": "yc",
    "name": "Standard Cyborg",
    "description": "Buid, test and deploy perception applications",
    "logo": "https://bookface-images.s3.amazonaws.com/small_logos/ea641cf296beace7a7288415d4808dc519f3a987.png",
    "website": "http://standardcyborg.com",
    "location": "San Francisco, CA, USA",
    "region": "United States of America",
    "subregion": "",
    "tags": [
      "Healthcare",
      "Medical Devices",
      "Machine Learning",
      "Computer Vision",
      "Open Source"
    ],
    "year": 2015,
    "program": "YC Winter 2015",
    "programSlugs": [
      "yc-winter-2015"
    ],
    "isExit": false,
    "isUnicorn": false,
    "isBCorp": false,
    "isCurrentSession": false,
    "social": {
      "linkedin": "",
      "twitter": "",
      "facebook": "",
      "crunchbase": ""
    },
    "extra": {}
  },
  {
    "source": "yc",
    "name": "Mashgin",
    "description": "Self-Checkout using Computer Vision.",
    "logo": "https://bookface-images.s3.amazonaws.com/small_logos/bd7ff2b3db9bbbc82a79afababdad873d16b6e54.png",
    "website": "http://mashgin.com",
    "location": "Palo Alto, CA, USA",
    "region": "United States of America",
    "subregion": "",
    "tags": [
      "Retail",
      "Artificial Intelligence",
      "Cashierless Checkout",
      "Deep Learning",
      "Hardware",
      "Computer Vision"
    ],
    "year": 2015,
    "program": "YC Winter 2015",
    "programSlugs": [
      "yc-winter-2015"
    ],
    "isExit": false,
    "isUnicorn": false,
    "isBCorp": false,
    "isCurrentSession": false,
    "social": {
      "linkedin": "",
      "twitter": "",
      "facebook": "",
      "crunchbase": ""
    },
    "extra": {}
  },
  {
    "source": "yc",
    "name": "Prayas Analytics",
    "description": "A/B testing for brick-and-mortar stores.",
    "logo": "https://bookface-images.s3.amazonaws.com/small_logos/5239f1a49fa06d125e98d56bb9e5a5fd04d9f05a.png",
    "website": "http://prayasanalytics.com",
    "location": "New York, NY, USA",
    "region": "United States of America",
    "subregion": "",
    "tags": [
      "Retail",
      "SaaS",
      "Computer Vision",
      "Retail Tech"
    ],
    "year": 2015,
    "program": "YC Summer 2015",
    "programSlugs": [
      "yc-summer-2015"
    ],
    "isExit": false,
    "isUnicorn": false,
    "isBCorp": false,
    "isCurrentSession": false,
    "social": {
      "linkedin": "",
      "twitter": "",
      "facebook": "",
      "crunchbase": ""
    },
    "extra": {}
  },
  {
    "source": "yc",
    "name": "Reduced Energy Microsystems",
    "description": "Building the lowest-power silicon for embedded deep learning and…",
    "logo": "/company/thumb/missing.png",
    "website": "http://remicro.com",
    "location": "San Francisco, CA, USA",
    "region": "United States of America",
    "subregion": "",
    "tags": [
      "Industrials",
      "Manufacturing and Robotics",
      "Artificial Intelligence",
      "Hardware",
      "Computer Vision",
      "Energy"
    ],
    "year": 2015,
    "program": "YC Summer 2015",
    "programSlugs": [
      "yc-summer-2015"
    ],
    "isExit": false,
    "isUnicorn": false,
    "isBCorp": false,
    "isCurrentSession": false,
    "social": {
      "linkedin": "",
      "twitter": "",
      "facebook": "",
      "crunchbase": ""
    },
    "extra": {}
  },
  {
    "source": "yc",
    "name": "Shape (ShapeScale)",
    "description": "ShapeScale is a personal 3D scanner and fitness tracker that…",
    "logo": "https://bookface-images.s3.amazonaws.com/small_logos/51a78fd63bb7c35e64c4b0654f44569b121ca09b.png",
    "website": "https://shapescale.com",
    "location": "San Francisco, CA, USA",
    "region": "United States of America",
    "subregion": "",
    "tags": [
      "Consumer",
      "Consumer Electronics",
      "Hardware",
      "Computer Vision",
      "Consumer Health Services"
    ],
    "year": 2015,
    "program": "YC Summer 2015",
    "programSlugs": [
      "yc-summer-2015"
    ],
    "isExit": false,
    "isUnicorn": false,
    "isBCorp": false,
    "isCurrentSession": false,
    "social": {
      "linkedin": "",
      "twitter": "",
      "facebook": "",
      "crunchbase": ""
    },
    "extra": {}
  },
  {
    "source": "yc",
    "name": "Focal Systems",
    "description": "Building the Operating System for B&M Retail using Deep Learning",
    "logo": "https://bookface-images.s3.amazonaws.com/small_logos/e25ba04ae8686807d958c48f1372502741b4b2e3.png",
    "website": "http://www.focal.systems",
    "location": "San Francisco, CA, USA; Toronto, ON, Canada; London, England, United Kingdom",
    "region": "United States of America",
    "subregion": "",
    "tags": [
      "Retail",
      "Deep Learning",
      "Grocery",
      "Computer Vision"
    ],
    "year": 2016,
    "program": "YC Winter 2016",
    "programSlugs": [
      "yc-winter-2016"
    ],
    "isExit": false,
    "isUnicorn": false,
    "isBCorp": false,
    "isCurrentSession": false,
    "social": {
      "linkedin": "",
      "twitter": "",
      "facebook": "",
      "crunchbase": ""
    },
    "extra": {}
  },
  {
    "source": "yc",
    "name": "Caper",
    "description": "Plug-and-play cashier-less retail powered by computer vision and AI",
    "logo": "https://bookface-images.s3.amazonaws.com/small_logos/45034c22d81491a4e49c2c46c3c822d2d820941d.png",
    "website": "https://www.caper.ai/",
    "location": "",
    "region": "Unspecified",
    "subregion": "",
    "tags": [
      "Retail",
      "Artificial Intelligence",
      "Cashierless Checkout",
      "Computer Vision",
      "Retail Tech"
    ],
    "year": 2016,
    "program": "YC Winter 2016",
    "programSlugs": [
      "yc-winter-2016"
    ],
    "isExit": true,
    "isUnicorn": false,
    "isBCorp": false,
    "isCurrentSession": false,
    "social": {
      "linkedin": "",
      "twitter": "",
      "facebook": "",
      "crunchbase": ""
    },
    "extra": {}
  },
  {
    "source": "yc",
    "name": "Iris Automation",
    "description": "Enabling autonomous drone operations globally through AI software",
    "logo": "/company/thumb/missing.png",
    "website": "http://www.irisonboard.com",
    "location": "San Francisco, CA, USA; Remote",
    "region": "United States of America",
    "subregion": "",
    "tags": [
      "Industrials",
      "Drones",
      "Computer Vision",
      "AI"
    ],
    "year": 2016,
    "program": "YC Summer 2016",
    "programSlugs": [
      "yc-summer-2016"
    ],
    "isExit": true,
    "isUnicorn": false,
    "isBCorp": false,
    "isCurrentSession": false,
    "social": {
      "linkedin": "",
      "twitter": "",
      "facebook": "",
      "crunchbase": ""
    },
    "extra": {}
  },
  {
    "source": "yc",
    "name": "CrowdAI",
    "description": "CrowdAI is the world's leading no-code platform for vision AI",
    "logo": "https://bookface-images.s3.amazonaws.com/small_logos/65641ddd8516f01cc3bf87dd2c876cd999d398f0.png",
    "website": "https://crowdai.com/",
    "location": "San Francisco, CA, USA",
    "region": "United States of America",
    "subregion": "",
    "tags": [
      "Machine Learning",
      "Computer Vision"
    ],
    "year": 2016,
    "program": "YC Summer 2016",
    "programSlugs": [
      "yc-summer-2016"
    ],
    "isExit": true,
    "isUnicorn": false,
    "isBCorp": false,
    "isCurrentSession": false,
    "social": {
      "linkedin": "",
      "twitter": "",
      "facebook": "",
      "crunchbase": ""
    },
    "extra": {}
  },
  {
    "source": "yc",
    "name": "Ambient.ai",
    "description": "AI company transforming enterprise physical security to prevent…",
    "logo": "https://bookface-images.s3.amazonaws.com/small_logos/624d0ce6f387431048bed692cfded210ffc7d139.png",
    "website": "https://ambient.ai",
    "location": "San Francisco, CA, USA; San Jose, CA, USA",
    "region": "United States of America",
    "subregion": "",
    "tags": [
      "Security",
      "Computer Vision",
      "AI"
    ],
    "year": 2017,
    "program": "YC Winter 2017",
    "programSlugs": [
      "yc-winter-2017"
    ],
    "isExit": false,
    "isUnicorn": false,
    "isBCorp": false,
    "isCurrentSession": false,
    "social": {
      "linkedin": "",
      "twitter": "",
      "facebook": "",
      "crunchbase": ""
    },
    "extra": {}
  },
  {
    "source": "yc",
    "name": "Veryfi, Inc.",
    "description": "Document AI. One API Call.",
    "logo": "https://bookface-images.s3.amazonaws.com/small_logos/b363a44bfe1278786c4092bd157ce82f208e1a21.png",
    "website": "https://www.veryfi.com/",
    "location": "San Francisco, CA, USA",
    "region": "United States of America",
    "subregion": "",
    "tags": [
      "Artificial Intelligence",
      "Computer Vision",
      "Finance",
      "API",
      "AI"
    ],
    "year": 2017,
    "program": "YC Winter 2017",
    "programSlugs": [
      "yc-winter-2017"
    ],
    "isExit": false,
    "isUnicorn": false,
    "isBCorp": false,
    "isCurrentSession": false,
    "social": {
      "linkedin": "",
      "twitter": "",
      "facebook": "",
      "crunchbase": ""
    },
    "extra": {}
  },
  {
    "source": "yc",
    "name": "Mirror AI",
    "description": "App that turns selfie photos into thousand emoji that look like you…",
    "logo": "https://bookface-images.s3.amazonaws.com/small_logos/410226e6cc4a405060b8845ca57a12726472ea14.png",
    "website": "http://mirror-ai.com",
    "location": "San Francisco, CA, USA; Remote",
    "region": "United States of America",
    "subregion": "",
    "tags": [
      "Consumer",
      "Social",
      "Computer Vision",
      "Entertainment"
    ],
    "year": 2017,
    "program": "YC Winter 2017",
    "programSlugs": [
      "yc-winter-2017"
    ],
    "isExit": false,
    "isUnicorn": false,
    "isBCorp": false,
    "isCurrentSession": false,
    "social": {
      "linkedin": "",
      "twitter": "",
      "facebook": "",
      "crunchbase": ""
    },
    "extra": {}
  },
  {
    "source": "yc",
    "name": "Skyways",
    "description": "Creating a new form of air transportation to advance our civilization",
    "logo": "https://bookface-images.s3.amazonaws.com/small_logos/6732fcb5c7c414475034015c2f1a9fa75a9f12a7.png",
    "website": "http://skyways.com",
    "location": "Austin, TX, USA",
    "region": "United States of America",
    "subregion": "",
    "tags": [
      "Industrials",
      "Drones",
      "Air Taxis",
      "Robotics",
      "Computer Vision",
      "AI",
      "ML"
    ],
    "year": 2017,
    "program": "YC Summer 2017",
    "programSlugs": [
      "yc-summer-2017"
    ],
    "isExit": false,
    "isUnicorn": false,
    "isBCorp": false,
    "isCurrentSession": false,
    "social": {
      "linkedin": "",
      "twitter": "",
      "facebook": "",
      "crunchbase": ""
    },
    "extra": {}
  },
  {
    "source": "yc",
    "name": "Jido Maps",
    "description": "Turn your data into a deployed computer vision model",
    "logo": "https://bookface-images.s3.amazonaws.com/small_logos/788dc05b2141606cea9f6805759306ec0ea99f5e.png",
    "website": "https://jidomaps.com/",
    "location": "Berkeley, CA, USA; San Francisco, CA, USA; Remote",
    "region": "United States of America",
    "subregion": "",
    "tags": [
      "Infrastructure",
      "Deep Learning",
      "Indoor Mapping",
      "Machine Learning",
      "Computer Vision"
    ],
    "year": 2018,
    "program": "YC Winter 2018",
    "programSlugs": [
      "yc-winter-2018"
    ],
    "isExit": true,
    "isUnicorn": false,
    "isBCorp": false,
    "isCurrentSession": false,
    "social": {
      "linkedin": "",
      "twitter": "",
      "facebook": "",
      "crunchbase": ""
    },
    "extra": {}
  },
  {
    "source": "yc",
    "name": "Activeloop",
    "description": "Database for AI",
    "logo": "https://bookface-images.s3.amazonaws.com/small_logos/c516ed5054847ecb1afb63f795f712b8d5c7f23d.png",
    "website": "https://activeloop.ai/",
    "location": "San Francisco, CA, USA; Mountain View, CA, USA",
    "region": "United States of America",
    "subregion": "",
    "tags": [
      "Infrastructure",
      "Computational Storage",
      "Deep Learning",
      "Generative AI",
      "Computer Vision",
      "Open Source"
    ],
    "year": 2018,
    "program": "YC Summer 2018",
    "programSlugs": [
      "yc-summer-2018"
    ],
    "isExit": false,
    "isUnicorn": false,
    "isBCorp": false,
    "isCurrentSession": false,
    "social": {
      "linkedin": "",
      "twitter": "",
      "facebook": "",
      "crunchbase": ""
    },
    "extra": {}
  },
  {
    "source": "yc",
    "name": "LabelFlow",
    "description": "GitHub for visual data",
    "logo": "https://bookface-images.s3.amazonaws.com/small_logos/799423cdb14bc1fbe4eb1d647eedf74d0a22e8c7.png",
    "website": "https://labelflow.ai/",
    "location": "Nantes, Pays de la Loire, France; Remote",
    "region": "France",
    "subregion": "",
    "tags": [
      "Engineering, Product and Design",
      "Computer Vision",
      "Data Engineering",
      "AI"
    ],
    "year": 2018,
    "program": "YC Summer 2018",
    "programSlugs": [
      "yc-summer-2018"
    ],
    "isExit": false,
    "isUnicorn": false,
    "isBCorp": false,
    "isCurrentSession": false,
    "social": {
      "linkedin": "",
      "twitter": "",
      "facebook": "",
      "crunchbase": ""
    },
    "extra": {}
  },
  {
    "source": "yc",
    "name": "Overview",
    "description": "Reshaping industrial quality with AI, hardware, and software",
    "logo": "https://bookface-images.s3.amazonaws.com/small_logos/cd1326e4f02e779f1009ae931cfeb26eb1eb20b7.png",
    "website": "https://overview.ai",
    "location": "San Francisco, CA, USA",
    "region": "United States of America",
    "subregion": "",
    "tags": [
      "Industrials",
      "Manufacturing and Robotics",
      "Deep Learning",
      "IoT",
      "Computer Vision",
      "Manufacturing",
      "AI"
    ],
    "year": 2019,
    "program": "YC Winter 2019",
    "programSlugs": [
      "yc-winter-2019"
    ],
    "isExit": false,
    "isUnicorn": false,
    "isBCorp": false,
    "isCurrentSession": false,
    "social": {
      "linkedin": "",
      "twitter": "",
      "facebook": "",
      "crunchbase": ""
    },
    "extra": {}
  },
  {
    "source": "yc",
    "name": "Sorting Robotics",
    "description": "We create automation technology for the cannabis industry.",
    "logo": "https://bookface-images.s3.amazonaws.com/small_logos/2dfc5eeb06e8051af24bd5a9c7758dbe219fba21.png",
    "website": "https://www.sortingrobotics.com/",
    "location": "Los Angeles, CA, USA",
    "region": "United States of America",
    "subregion": "",
    "tags": [
      "Supply Chain and Logistics",
      "Robotic Process Automation",
      "Robotics",
      "Computer Vision"
    ],
    "year": 2019,
    "program": "YC Winter 2019",
    "programSlugs": [
      "yc-winter-2019"
    ],
    "isExit": false,
    "isUnicorn": false,
    "isBCorp": false,
    "isCurrentSession": false,
    "social": {
      "linkedin": "",
      "twitter": "",
      "facebook": "",
      "crunchbase": ""
    },
    "extra": {}
  },
  {
    "source": "yc",
    "name": "Aura Vision",
    "description": "In-store analytics AI assistant to fix your retail stores",
    "logo": "https://bookface-images.s3.amazonaws.com/small_logos/06dd0022a30071b010e7c41ab3e012079397a6d2.png",
    "website": "https://auravision.ai",
    "location": "London, England, United Kingdom",
    "region": "United Kingdom",
    "subregion": "",
    "tags": [
      "Retail",
      "SaaS",
      "IoT",
      "Computer Vision"
    ],
    "year": 2019,
    "program": "YC Winter 2019",
    "programSlugs": [
      "yc-winter-2019"
    ],
    "isExit": false,
    "isUnicorn": false,
    "isBCorp": false,
    "isCurrentSession": false,
    "social": {
      "linkedin": "",
      "twitter": "",
      "facebook": "",
      "crunchbase": ""
    },
    "extra": {}
  },
  {
    "source": "yc",
    "name": "Allure Systems",
    "description": "A.I. to create stunning fashion images for eCommerce. ",
    "logo": "https://bookface-images.s3.amazonaws.com/small_logos/876f66dff22e97cba80fe969792f2c63dd568d79.png",
    "website": "http://www.alluresystems.com/",
    "location": "New York, NY, USA",
    "region": "United States of America",
    "subregion": "",
    "tags": [
      "Retail",
      "Generative AI",
      "Computer Vision",
      "E-commerce",
      "AI"
    ],
    "year": 2019,
    "program": "YC Winter 2019",
    "programSlugs": [
      "yc-winter-2019"
    ],
    "isExit": true,
    "isUnicorn": false,
    "isBCorp": false,
    "isCurrentSession": false,
    "social": {
      "linkedin": "",
      "twitter": "",
      "facebook": "",
      "crunchbase": ""
    },
    "extra": {}
  },
  {
    "source": "yc",
    "name": "Traces",
    "description": "Transform your video monitoring with AI",
    "logo": "https://bookface-images.s3.amazonaws.com/small_logos/95c9d28f031050f88288e5b80195b4ca69c2dd41.png",
    "website": "https://www.traces.ai",
    "location": "San Francisco, CA, USA; Mountain View, CA, USA",
    "region": "United States of America",
    "subregion": "",
    "tags": [
      "Security",
      "Artificial Intelligence",
      "Deep Learning",
      "Computer Vision"
    ],
    "year": 2019,
    "program": "YC Summer 2019",
    "programSlugs": [
      "yc-summer-2019"
    ],
    "isExit": false,
    "isUnicorn": false,
    "isBCorp": false,
    "isCurrentSession": false,
    "social": {
      "linkedin": "",
      "twitter": "",
      "facebook": "",
      "crunchbase": ""
    },
    "extra": {}
  },
  {
    "source": "yc",
    "name": "Taiv",
    "description": "AI-powered tech that makes business TV smarter, engaging, and…",
    "logo": "https://bookface-images.s3.amazonaws.com/small_logos/86c32f1abe7d2cba987238d8fbcc9048fc815dfe.png",
    "website": "https://taiv.tv",
    "location": "Winnipeg, MB, Canada",
    "region": "Canada",
    "subregion": "",
    "tags": [
      "Marketing",
      "Artificial Intelligence",
      "Marketplace",
      "Computer Vision",
      "Advertising"
    ],
    "year": 2020,
    "program": "YC Winter 2020",
    "programSlugs": [
      "yc-winter-2020"
    ],
    "isExit": false,
    "isUnicorn": false,
    "isBCorp": false,
    "isCurrentSession": false,
    "social": {
      "linkedin": "",
      "twitter": "",
      "facebook": "",
      "crunchbase": ""
    },
    "extra": {}
  },
  {
    "source": "yc",
    "name": "Photoroom",
    "description": "Power commerce photography with generative AI",
    "logo": "https://bookface-images.s3.amazonaws.com/small_logos/e5f5e5ed0c922fb566fac15578940996a8f6a930.png",
    "website": "https://photoroom.com/",
    "location": "Paris, Île-de-France, France",
    "region": "France",
    "subregion": "",
    "tags": [
      "Consumer",
      "Content",
      "Generative AI",
      "Computer Vision",
      "Design Tools",
      "API",
      "AI"
    ],
    "year": 2020,
    "program": "YC Summer 2020",
    "programSlugs": [
      "yc-summer-2020"
    ],
    "isExit": false,
    "isUnicorn": false,
    "isBCorp": false,
    "isCurrentSession": false,
    "social": {
      "linkedin": "",
      "twitter": "",
      "facebook": "",
      "crunchbase": ""
    },
    "extra": {}
  },
  {
    "source": "yc",
    "name": "Oda",
    "description": "AI Agent for Home Design",
    "logo": "https://bookface-images.s3.amazonaws.com/small_logos/b282b3863a1e15b0e08e9b79cf5ac972840f5523.png",
    "website": "https://www.odastudio.ai/?ref=yc",
    "location": "Los Angeles, CA, USA; Remote",
    "region": "United States of America",
    "subregion": "",
    "tags": [
      "Marketing",
      "Machine Learning",
      "Computer Vision",
      "E-commerce",
      "AI Assistant"
    ],
    "year": 2020,
    "program": "YC Winter 2020",
    "programSlugs": [
      "yc-winter-2020"
    ],
    "isExit": false,
    "isUnicorn": false,
    "isBCorp": false,
    "isCurrentSession": false,
    "social": {
      "linkedin": "",
      "twitter": "",
      "facebook": "",
      "crunchbase": ""
    },
    "extra": {}
  },
  {
    "source": "yc",
    "name": "Roboflow",
    "description": "🖼️ Give your software the sense of sight.",
    "logo": "https://bookface-images.s3.amazonaws.com/small_logos/ba0036069bd338a4c6188cb137722d8f584d0016.png",
    "website": "https://roboflow.com",
    "location": "San Francisco, CA, USA",
    "region": "United States of America",
    "subregion": "",
    "tags": [
      "Engineering, Product and Design",
      "Developer Tools",
      "Machine Learning",
      "Computer Vision",
      "Enterprise",
      "AI"
    ],
    "year": 2020,
    "program": "YC Summer 2020",
    "programSlugs": [
      "yc-summer-2020"
    ],
    "isExit": false,
    "isUnicorn": false,
    "isBCorp": false,
    "isCurrentSession": false,
    "social": {
      "linkedin": "",
      "twitter": "",
      "facebook": "",
      "crunchbase": ""
    },
    "extra": {}
  },
  {
    "source": "yc",
    "name": "Hypermile",
    "description": "Driver co-pilot to make trucking more efficient",
    "logo": "https://bookface-images.s3.amazonaws.com/small_logos/b25c7b5a70e0fab68abb8837d04d772f89ba6623.png",
    "website": "https://hypermile.ai",
    "location": "London, England, United Kingdom",
    "region": "United Kingdom",
    "subregion": "",
    "tags": [
      "Engineering, Product and Design",
      "Autonomous Trucking",
      "Computer Vision",
      "Logistics",
      "Climate"
    ],
    "year": 2020,
    "program": "YC Summer 2020",
    "programSlugs": [
      "yc-summer-2020"
    ],
    "isExit": true,
    "isUnicorn": false,
    "isBCorp": false,
    "isCurrentSession": false,
    "social": {
      "linkedin": "",
      "twitter": "",
      "facebook": "",
      "crunchbase": ""
    },
    "extra": {}
  },
  {
    "source": "yc",
    "name": "Hellometer",
    "description": "Making fast food faster",
    "logo": "https://bookface-images.s3.amazonaws.com/small_logos/a6ce1063846053edd4d35f8feec4badb3dc82dd8.png",
    "website": "https://hellometer.io/",
    "location": "Los Angeles, CA, USA",
    "region": "United States of America",
    "subregion": "",
    "tags": [
      "Retail",
      "SaaS",
      "Computer Vision"
    ],
    "year": 2020,
    "program": "YC Summer 2020",
    "programSlugs": [
      "yc-summer-2020"
    ],
    "isExit": false,
    "isUnicorn": false,
    "isBCorp": false,
    "isCurrentSession": false,
    "social": {
      "linkedin": "",
      "twitter": "",
      "facebook": "",
      "crunchbase": ""
    },
    "extra": {}
  },
  {
    "source": "yc",
    "name": "SBX Robotics",
    "description": "Synthetic data for better vision.",
    "logo": "https://bookface-images.s3.amazonaws.com/small_logos/511a67e1066575bd8304628248a6a9307430e18f.png",
    "website": "https://www.sbxrobotics.com/",
    "location": "Toronto, ON, Canada",
    "region": "Canada",
    "subregion": "",
    "tags": [
      "Engineering, Product and Design",
      "Artificial Intelligence",
      "Machine Learning",
      "Robotics",
      "Computer Vision",
      "Data Engineering"
    ],
    "year": 2021,
    "program": "YC Winter 2021",
    "programSlugs": [
      "yc-winter-2021"
    ],
    "isExit": false,
    "isUnicorn": false,
    "isBCorp": false,
    "isCurrentSession": false,
    "social": {
      "linkedin": "",
      "twitter": "",
      "facebook": "",
      "crunchbase": ""
    },
    "extra": {}
  },
  {
    "source": "yc",
    "name": "Segments.ai",
    "description": "Build better computer vision models by building better datasets",
    "logo": "https://bookface-images.s3.amazonaws.com/small_logos/ac88c08aefaf0753bc9d29d8d7ced656148b852c.png",
    "website": "https://segments.ai",
    "location": "Brussels, Brussels, Belgium; Remote",
    "region": "Belgium",
    "subregion": "",
    "tags": [
      "Engineering, Product and Design",
      "Deep Learning",
      "Developer Tools",
      "Computer Vision"
    ],
    "year": 2021,
    "program": "YC Winter 2021",
    "programSlugs": [
      "yc-winter-2021"
    ],
    "isExit": true,
    "isUnicorn": false,
    "isBCorp": false,
    "isCurrentSession": false,
    "social": {
      "linkedin": "",
      "twitter": "",
      "facebook": "",
      "crunchbase": ""
    },
    "extra": {}
  },
  {
    "source": "yc",
    "name": "ClipDrop",
    "description": "Turn regular mobile photos into professional product visuals",
    "logo": "https://bookface-images.s3.amazonaws.com/small_logos/3bfd4a654412f2405d3448ad846ed61f08074a04.png",
    "website": "https://clipdrop.co",
    "location": "Paris, Île-de-France, France; Remote",
    "region": "France",
    "subregion": "",
    "tags": [
      "Consumer",
      "Content",
      "SaaS",
      "Computer Vision",
      "Design Tools"
    ],
    "year": 2021,
    "program": "YC Winter 2021",
    "programSlugs": [
      "yc-winter-2021"
    ],
    "isExit": true,
    "isUnicorn": false,
    "isBCorp": false,
    "isCurrentSession": false,
    "social": {
      "linkedin": "",
      "twitter": "",
      "facebook": "",
      "crunchbase": ""
    },
    "extra": {}
  },
  {
    "source": "yc",
    "name": "LightTwist",
    "description": "Record video in a photorealistic virtual studio all from your browser",
    "logo": "https://bookface-images.s3.amazonaws.com/small_logos/69063ba25c16af04c5fdb92fd680138cd0eaea3b.png",
    "website": "https://lighttwist.com",
    "location": "Boulder, CO, USA; Remote",
    "region": "United States of America",
    "subregion": "",
    "tags": [
      "Engineering, Product and Design",
      "Augmented Reality",
      "Computer Vision",
      "Design Tools"
    ],
    "year": 2021,
    "program": "YC Winter 2021",
    "programSlugs": [
      "yc-winter-2021"
    ],
    "isExit": false,
    "isUnicorn": false,
    "isBCorp": false,
    "isCurrentSession": false,
    "social": {
      "linkedin": "",
      "twitter": "",
      "facebook": "",
      "crunchbase": ""
    },
    "extra": {}
  },
  {
    "source": "yc",
    "name": "MarqVision",
    "description": "IP operating software for brands and content companies",
    "logo": "https://bookface-images.s3.amazonaws.com/small_logos/b993f487d88442acd03e44f8b8ba2ff9dd1c72c7.png",
    "website": "https://www.marqvision.com/",
    "location": "San Francisco, CA, USA",
    "region": "United States of America",
    "subregion": "",
    "tags": [
      "Artificial Intelligence",
      "SaaS",
      "Computer Vision",
      "LegalTech"
    ],
    "year": 2021,
    "program": "YC Summer 2021",
    "programSlugs": [
      "yc-summer-2021"
    ],
    "isExit": false,
    "isUnicorn": false,
    "isBCorp": false,
    "isCurrentSession": false,
    "social": {
      "linkedin": "",
      "twitter": "",
      "facebook": "",
      "crunchbase": ""
    },
    "extra": {}
  },
  {
    "source": "yc",
    "name": "SnapCalorie",
    "description": "Single photo nutrition tracking.",
    "logo": "https://bookface-images.s3.amazonaws.com/small_logos/8fb8d3ff1ae8ec164dd664632cc42c03b043c549.png",
    "website": "https://www.snapcalorie.com/",
    "location": "New York, NY, USA; Washington, DC, USA",
    "region": "United States of America",
    "subregion": "",
    "tags": [
      "Consumer",
      "Computer Vision",
      "Fitness",
      "AI"
    ],
    "year": 2021,
    "program": "YC Summer 2021",
    "programSlugs": [
      "yc-summer-2021"
    ],
    "isExit": false,
    "isUnicorn": false,
    "isBCorp": false,
    "isCurrentSession": false,
    "social": {
      "linkedin": "",
      "twitter": "",
      "facebook": "",
      "crunchbase": ""
    },
    "extra": {}
  },
  {
    "source": "yc",
    "name": "Milky Way AI",
    "description": "Mobile app for CPG brands to connect to millions of stores globally",
    "logo": "https://bookface-images.s3.amazonaws.com/small_logos/2efe7f33198c252ca563c3f685bd5e290b4064d2.png",
    "website": "https://milkyway.ai/",
    "location": "Singapore, Singapore; Remote",
    "region": "Singapore",
    "subregion": "",
    "tags": [
      "Retail",
      "Artificial Intelligence",
      "SaaS",
      "Computer Vision"
    ],
    "year": 2021,
    "program": "YC Summer 2021",
    "programSlugs": [
      "yc-summer-2021"
    ],
    "isExit": false,
    "isUnicorn": false,
    "isBCorp": false,
    "isCurrentSession": false,
    "social": {
      "linkedin": "",
      "twitter": "",
      "facebook": "",
      "crunchbase": ""
    },
    "extra": {}
  },
  {
    "source": "yc",
    "name": "Mach9",
    "description": "AI-native CAD software for civil engineering",
    "logo": "https://bookface-images.s3.amazonaws.com/small_logos/05390d32227edd1416d7dc545801c3fc59e2ac15.png",
    "website": "https://www.mach9.ai/",
    "location": "San Francisco, CA, USA",
    "region": "United States of America",
    "subregion": "",
    "tags": [
      "Engineering, Product and Design",
      "Artificial Intelligence",
      "Machine Learning",
      "Computer Vision",
      "Design Tools",
      "Infrastructure"
    ],
    "year": 2021,
    "program": "YC Summer 2021",
    "programSlugs": [
      "yc-summer-2021"
    ],
    "isExit": false,
    "isUnicorn": false,
    "isBCorp": false,
    "isCurrentSession": false,
    "social": {
      "linkedin": "",
      "twitter": "",
      "facebook": "",
      "crunchbase": ""
    },
    "extra": {}
  },
  {
    "source": "yc",
    "name": "Tenyks",
    "description": "The World's Most Versatile Video Answering Engine ",
    "logo": "https://bookface-images.s3.amazonaws.com/small_logos/7006298209ca0e4b566665242aadbc44f58b1d59.png",
    "website": "http://tenyks.ai/",
    "location": "Cambridge, England, United Kingdom; Remote",
    "region": "United Kingdom",
    "subregion": "",
    "tags": [
      "Artificial Intelligence",
      "Computer Vision",
      "Video",
      "AI",
      "AI Assistant"
    ],
    "year": 2021,
    "program": "YC Summer 2021",
    "programSlugs": [
      "yc-summer-2021"
    ],
    "isExit": false,
    "isUnicorn": false,
    "isBCorp": false,
    "isCurrentSession": false,
    "social": {
      "linkedin": "",
      "twitter": "",
      "facebook": "",
      "crunchbase": ""
    },
    "extra": {}
  },
  {
    "source": "yc",
    "name": "Eventual",
    "description": "Building the AI data engine for any modality and scale",
    "logo": "https://bookface-images.s3.amazonaws.com/small_logos/f429c16ee024d738c1b758e7c2d0ca5d811f204b.png",
    "website": "https://www.daft.ai/",
    "location": "San Francisco, CA, USA",
    "region": "United States of America",
    "subregion": "",
    "tags": [
      "Infrastructure",
      "Computer Vision"
    ],
    "year": 2022,
    "program": "YC Winter 2022",
    "programSlugs": [
      "yc-winter-2022"
    ],
    "isExit": false,
    "isUnicorn": false,
    "isBCorp": false,
    "isCurrentSession": false,
    "social": {
      "linkedin": "",
      "twitter": "",
      "facebook": "",
      "crunchbase": ""
    },
    "extra": {}
  },
  {
    "source": "yc",
    "name": "Cerrion",
    "description": "Video AI to automatically detect and respond to production line…",
    "logo": "https://bookface-images.s3.amazonaws.com/small_logos/a2cfaa4757206398a9d1678a216905dc2a248f11.png",
    "website": "https://www.cerrion.com/",
    "location": "Zürich, ZH, Switzerland",
    "region": "Switzerland",
    "subregion": "",
    "tags": [
      "Industrials",
      "Artificial Intelligence",
      "Deep Learning",
      "Computer Vision",
      "Video",
      "Manufacturing"
    ],
    "year": 2022,
    "program": "YC Summer 2022",
    "programSlugs": [
      "yc-summer-2022"
    ],
    "isExit": false,
    "isUnicorn": false,
    "isBCorp": false,
    "isCurrentSession": false,
    "social": {
      "linkedin": "",
      "twitter": "",
      "facebook": "",
      "crunchbase": ""
    },
    "extra": {}
  },
  {
    "source": "yc",
    "name": "Apply Design",
    "description": "Helping realtors showcase the full potential of their properties",
    "logo": "https://bookface-images.s3.amazonaws.com/small_logos/731fd6f22634f935a03484945b5b569dae8c8ed9.png",
    "website": "http://www.applydesign.io",
    "location": "Tel Aviv-Yafo, Tel Aviv District, Israel",
    "region": "Israel",
    "subregion": "",
    "tags": [
      "Real Estate and Construction",
      "Generative AI",
      "SaaS",
      "Computer Vision",
      "Proptech",
      "E-commerce"
    ],
    "year": 2022,
    "program": "YC Summer 2022",
    "programSlugs": [
      "yc-summer-2022"
    ],
    "isExit": false,
    "isUnicorn": false,
    "isBCorp": false,
    "isCurrentSession": false,
    "social": {
      "linkedin": "",
      "twitter": "",
      "facebook": "",
      "crunchbase": ""
    },
    "extra": {}
  },
  {
    "source": "yc",
    "name": "CAPSULE",
    "description": "Buy anything you find on social media",
    "logo": "https://bookface-images.s3.amazonaws.com/small_logos/19f195e9a25d1cff1f914f65ceb3e7458c6d52b9.png",
    "website": "https://www.shopcapsule.ai/",
    "location": "San Francisco, CA, USA",
    "region": "United States of America",
    "subregion": "",
    "tags": [
      "Consumer",
      "Apparel and Cosmetics",
      "Artificial Intelligence",
      "Generative AI",
      "Machine Learning",
      "Computer Vision",
      "E-commerce"
    ],
    "year": 2022,
    "program": "YC Summer 2022",
    "programSlugs": [
      "yc-summer-2022"
    ],
    "isExit": false,
    "isUnicorn": false,
    "isBCorp": false,
    "isCurrentSession": false,
    "social": {
      "linkedin": "",
      "twitter": "",
      "facebook": "",
      "crunchbase": ""
    },
    "extra": {}
  },
  {
    "source": "yc",
    "name": "Scanbase",
    "description": "The API for Diagnostic Test Analysis (COVID-19, FLU, RSV, STD,…",
    "logo": "https://bookface-images.s3.amazonaws.com/small_logos/c9177f461ffabba1796fab772ec9f376ad91bf4e.png",
    "website": "https://www.scanbase.com",
    "location": "Los Angeles, CA, USA",
    "region": "United States of America",
    "subregion": "",
    "tags": [
      "Healthcare",
      "Diagnostics",
      "Machine Learning",
      "Computer Vision",
      "Health Tech",
      "Telemedicine",
      "AI"
    ],
    "year": 2023,
    "program": "YC Winter 2023",
    "programSlugs": [
      "yc-winter-2023"
    ],
    "isExit": false,
    "isUnicorn": false,
    "isBCorp": false,
    "isCurrentSession": false,
    "social": {
      "linkedin": "",
      "twitter": "",
      "facebook": "",
      "crunchbase": ""
    },
    "extra": {}
  },
  {
    "source": "yc",
    "name": "Dream3D",
    "description": "Generative AI Worlds",
    "logo": "https://bookface-images.s3.amazonaws.com/small_logos/dc5c128914787f1ad09c34983b9c40c1200da598.png",
    "website": "https://dream3d.com",
    "location": "New York, NY, USA",
    "region": "United States of America",
    "subregion": "",
    "tags": [
      "Engineering, Product and Design",
      "Generative AI",
      "Computer Vision",
      "AI"
    ],
    "year": 2023,
    "program": "YC Winter 2023",
    "programSlugs": [
      "yc-winter-2023"
    ],
    "isExit": false,
    "isUnicorn": false,
    "isBCorp": false,
    "isCurrentSession": false,
    "social": {
      "linkedin": "",
      "twitter": "",
      "facebook": "",
      "crunchbase": ""
    },
    "extra": {}
  },
  {
    "source": "yc",
    "name": "rex.fit",
    "description": "Automating nutrition tracking.",
    "logo": "https://bookface-images.s3.amazonaws.com/small_logos/c618208d2cb852eeff16409fb7e787701c395b91.png",
    "website": "https://www.rex.fit",
    "location": "San Francisco, CA, USA",
    "region": "United States of America",
    "subregion": "",
    "tags": [
      "Consumer",
      "Artificial Intelligence",
      "Hard Tech",
      "Computer Vision",
      "Consumer Health Services",
      "Fitness"
    ],
    "year": 2023,
    "program": "YC Winter 2023",
    "programSlugs": [
      "yc-winter-2023"
    ],
    "isExit": false,
    "isUnicorn": false,
    "isBCorp": false,
    "isCurrentSession": false,
    "social": {
      "linkedin": "",
      "twitter": "",
      "facebook": "",
      "crunchbase": ""
    },
    "extra": {}
  },
  {
    "source": "yc",
    "name": "MICSI",
    "description": "Higher resolution MRI with faster scan times.",
    "logo": "https://bookface-images.s3.amazonaws.com/small_logos/29d35560d45b90c5227b12877556942576e43627.png",
    "website": "https://www.micsi.co/",
    "location": "New York, NY, USA",
    "region": "United States of America",
    "subregion": "",
    "tags": [
      "Healthcare",
      "Diagnostics",
      "Computer Vision",
      "Medical Devices"
    ],
    "year": 2023,
    "program": "YC Summer 2023",
    "programSlugs": [
      "yc-summer-2023"
    ],
    "isExit": false,
    "isUnicorn": false,
    "isBCorp": false,
    "isCurrentSession": false,
    "social": {
      "linkedin": "",
      "twitter": "",
      "facebook": "",
      "crunchbase": ""
    },
    "extra": {}
  },
  {
    "source": "yc",
    "name": "Rimward",
    "description": "Low-false-positive intrusion detection for remote outdoor sites",
    "logo": "https://bookface-images.s3.amazonaws.com/small_logos/bd215af97ab581709a04ff6284c6091f29c2058e.png",
    "website": "https://rimward.ai/",
    "location": "Paris, Île-de-France, France",
    "region": "France",
    "subregion": "",
    "tags": [
      "Security",
      "Machine Learning",
      "Computer Vision",
      "Enterprise"
    ],
    "year": 2023,
    "program": "YC Summer 2023",
    "programSlugs": [
      "yc-summer-2023"
    ],
    "isExit": false,
    "isUnicorn": false,
    "isBCorp": false,
    "isCurrentSession": false,
    "social": {
      "linkedin": "",
      "twitter": "",
      "facebook": "",
      "crunchbase": ""
    },
    "extra": {}
  },
  {
    "source": "yc",
    "name": "sizeless",
    "description": "Instant 3D Digital Twins for Smarter Real Estate.",
    "logo": "https://bookface-images.s3.amazonaws.com/small_logos/90ad40c9214ea17e0132605fba1e092c86e8b9a0.png",
    "website": "https://www.sizeless.co",
    "location": "San Francisco, CA, USA",
    "region": "United States of America",
    "subregion": "",
    "tags": [
      "Real Estate and Construction",
      "Artificial Intelligence",
      "Computer Vision",
      "Real Estate",
      "Construction",
      "Energy"
    ],
    "year": 2023,
    "program": "YC Summer 2023",
    "programSlugs": [
      "yc-summer-2023"
    ],
    "isExit": false,
    "isUnicorn": false,
    "isBCorp": false,
    "isCurrentSession": false,
    "social": {
      "linkedin": "",
      "twitter": "",
      "facebook": "",
      "crunchbase": ""
    },
    "extra": {}
  },
  {
    "source": "yc",
    "name": "Aedilic",
    "description": "Open-Source AI-generated image/deepfake detection",
    "logo": "https://bookface-images.s3.amazonaws.com/small_logos/e453f612e8022f9284505dc7f70270165e918ea9.png",
    "website": "https://www.nonescape.com",
    "location": "San Francisco, CA, USA",
    "region": "United States of America",
    "subregion": "",
    "tags": [
      "Security",
      "Computer Vision",
      "AI"
    ],
    "year": 2024,
    "program": "YC Winter 2024",
    "programSlugs": [
      "yc-winter-2024"
    ],
    "isExit": false,
    "isUnicorn": false,
    "isBCorp": false,
    "isCurrentSession": false,
    "social": {
      "linkedin": "",
      "twitter": "",
      "facebook": "",
      "crunchbase": ""
    },
    "extra": {}
  },
  {
    "source": "yc",
    "name": "EdgeTrace",
    "description": "Describe It. Find It. Act On It.",
    "logo": "https://bookface-images.s3.amazonaws.com/small_logos/1a5e9f714f08ee19fe05c995f4d3940b758e86ef.png",
    "website": "https://edgetrace.ai",
    "location": "San Francisco, CA, USA",
    "region": "United States of America",
    "subregion": "",
    "tags": [
      "GovTech",
      "Computer Vision",
      "Video",
      "AI"
    ],
    "year": 2024,
    "program": "YC Winter 2024",
    "programSlugs": [
      "yc-winter-2024"
    ],
    "isExit": false,
    "isUnicorn": false,
    "isBCorp": false,
    "isCurrentSession": false,
    "social": {
      "linkedin": "",
      "twitter": "",
      "facebook": "",
      "crunchbase": ""
    },
    "extra": {}
  },
  {
    "source": "yc",
    "name": "Deepnight",
    "description": "Building The Next Generation of Night Vision Devices",
    "logo": "https://bookface-images.s3.amazonaws.com/small_logos/419c6b136773af60713e2a4301554b4ef1bbd8a9.png",
    "website": "https://www.deepnight.ai/",
    "location": "San Francisco, CA, USA",
    "region": "United States of America",
    "subregion": "",
    "tags": [
      "Industrials",
      "Defense",
      "Computer Vision",
      "AI"
    ],
    "year": 2024,
    "program": "YC Winter 2024",
    "programSlugs": [
      "yc-winter-2024"
    ],
    "isExit": false,
    "isUnicorn": false,
    "isBCorp": false,
    "isCurrentSession": false,
    "social": {
      "linkedin": "",
      "twitter": "",
      "facebook": "",
      "crunchbase": ""
    },
    "extra": {}
  },
  {
    "source": "yc",
    "name": "Dragoneye",
    "description": "Custom video detection models in less than 5 minutes",
    "logo": "https://bookface-images.s3.amazonaws.com/small_logos/354a00433e0332ff17869b4c08d6ee8d10b8a232.png",
    "website": "https://dragoneye.ai/",
    "location": "New York, NY, USA",
    "region": "United States of America",
    "subregion": "",
    "tags": [
      "Engineering, Product and Design",
      "Developer Tools",
      "Computer Vision",
      "AI",
      "ML"
    ],
    "year": 2024,
    "program": "YC Winter 2024",
    "programSlugs": [
      "yc-winter-2024"
    ],
    "isExit": false,
    "isUnicorn": false,
    "isBCorp": false,
    "isCurrentSession": false,
    "social": {
      "linkedin": "",
      "twitter": "",
      "facebook": "",
      "crunchbase": ""
    },
    "extra": {}
  },
  {
    "source": "yc",
    "name": "DigitalCarbon",
    "description": "Transform Images And Videos Into Immersive 3D With AI",
    "logo": "https://bookface-images.s3.amazonaws.com/small_logos/5cd96189d0726eb13cddf2279ecddbb8f1d37895.png",
    "website": "https://www.digitalcarbon.ai",
    "location": "San Francisco, CA, USA",
    "region": "United States of America",
    "subregion": "",
    "tags": [
      "Computer Vision",
      "Real Estate",
      "E-commerce",
      "AI"
    ],
    "year": 2024,
    "program": "YC Summer 2024",
    "programSlugs": [
      "yc-summer-2024"
    ],
    "isExit": false,
    "isUnicorn": false,
    "isBCorp": false,
    "isCurrentSession": false,
    "social": {
      "linkedin": "",
      "twitter": "",
      "facebook": "",
      "crunchbase": ""
    },
    "extra": {}
  },
  {
    "source": "yc",
    "name": "RunLocal AI",
    "description": "The first AI agent for optimizing ML model inference on edge hardware",
    "logo": "https://bookface-images.s3.amazonaws.com/small_logos/4f47cbbc26af6f2d783af0166e54e51212101bcc.png",
    "website": "https://runlocal.ai",
    "location": "London, England, United Kingdom",
    "region": "United Kingdom",
    "subregion": "",
    "tags": [
      "Engineering, Product and Design",
      "Developer Tools",
      "Computer Vision",
      "AI",
      "ML"
    ],
    "year": 2024,
    "program": "YC Summer 2024",
    "programSlugs": [
      "yc-summer-2024"
    ],
    "isExit": false,
    "isUnicorn": false,
    "isBCorp": false,
    "isCurrentSession": false,
    "social": {
      "linkedin": "",
      "twitter": "",
      "facebook": "",
      "crunchbase": ""
    },
    "extra": {}
  },
  {
    "source": "yc",
    "name": "Weel",
    "description": "GPS & dashcam smartphone app",
    "logo": "https://bookface-images.s3.amazonaws.com/small_logos/22dac63897681e1a31dc26b877ee786266ae0bff.png",
    "website": "https://weel.live/",
    "location": "New York, NY, USA",
    "region": "United States of America",
    "subregion": "",
    "tags": [
      "Consumer",
      "Transportation Services",
      "Augmented Reality",
      "Computer Vision",
      "Navigation",
      "Mobility",
      "Automotive"
    ],
    "year": 2024,
    "program": "YC Summer 2024",
    "programSlugs": [
      "yc-summer-2024"
    ],
    "isExit": false,
    "isUnicorn": false,
    "isBCorp": false,
    "isCurrentSession": false,
    "social": {
      "linkedin": "",
      "twitter": "",
      "facebook": "",
      "crunchbase": ""
    },
    "extra": {}
  },
  {
    "source": "yc",
    "name": "autarc",
    "description": "autarc is the agentic OS for energy installers.",
    "logo": "https://bookface-images.s3.amazonaws.com/small_logos/c6f422aa332e520cce9d631b8dfbcdfb14375c6e.png",
    "website": "https://www.autarc.energy/global",
    "location": "Berlin, Berlin, Germany",
    "region": "Germany",
    "subregion": "",
    "tags": [
      "Artificial Intelligence",
      "Lidar",
      "Computer Vision",
      "AI Assistant"
    ],
    "year": 2024,
    "program": "YC Summer 2024",
    "programSlugs": [
      "yc-summer-2024"
    ],
    "isExit": false,
    "isUnicorn": false,
    "isBCorp": false,
    "isCurrentSession": false,
    "social": {
      "linkedin": "",
      "twitter": "",
      "facebook": "",
      "crunchbase": ""
    },
    "extra": {}
  },
  {
    "source": "yc",
    "name": "Bucket Robotics",
    "description": "Defect detection for manufacturing built from CAD and synthetic data.",
    "logo": "https://bookface-images.s3.amazonaws.com/small_logos/55cc697d9f14eca5a5d45772ac14d97a83df16ae.png",
    "website": "https://bucket.bot",
    "location": "San Francisco, CA, USA",
    "region": "United States of America",
    "subregion": "",
    "tags": [
      "Industrials",
      "Manufacturing and Robotics",
      "Robotic Process Automation",
      "Robotics",
      "Computer Vision",
      "Manufacturing"
    ],
    "year": 2024,
    "program": "YC Summer 2024",
    "programSlugs": [
      "yc-summer-2024"
    ],
    "isExit": false,
    "isUnicorn": false,
    "isBCorp": false,
    "isCurrentSession": false,
    "social": {
      "linkedin": "",
      "twitter": "",
      "facebook": "",
      "crunchbase": ""
    },
    "extra": {}
  },
  {
    "source": "yc",
    "name": "Mecha Health",
    "description": "Foundation models to automate x-ray analysis for radiologists",
    "logo": "https://bookface-images.s3.amazonaws.com/small_logos/e851087b2c25e5bd175d39d8631791d74e04ebb1.png",
    "website": "https://www.mecha-health.ai/",
    "location": "San Francisco, CA, USA",
    "region": "United States of America",
    "subregion": "",
    "tags": [
      "Healthcare",
      "Artificial Intelligence",
      "Machine Learning",
      "Computer Vision",
      "Health Tech"
    ],
    "year": 2025,
    "program": "YC Winter 2025",
    "programSlugs": [
      "yc-winter-2025"
    ],
    "isExit": false,
    "isUnicorn": false,
    "isBCorp": false,
    "isCurrentSession": false,
    "social": {
      "linkedin": "",
      "twitter": "",
      "facebook": "",
      "crunchbase": ""
    },
    "extra": {}
  },
  {
    "source": "yc",
    "name": "Exla",
    "description": "An SDK to run transformer models anywhere",
    "logo": "https://bookface-images.s3.amazonaws.com/small_logos/94cd00784e37842fc455ee2fd7b22d487b0693cf.png",
    "website": "https://exla.ai/",
    "location": "San Francisco, CA, USA",
    "region": "United States of America",
    "subregion": "",
    "tags": [
      "Engineering, Product and Design",
      "Artificial Intelligence",
      "Edge Computing Semiconductors",
      "Computer Vision"
    ],
    "year": 2025,
    "program": "YC Winter 2025",
    "programSlugs": [
      "yc-winter-2025"
    ],
    "isExit": false,
    "isUnicorn": false,
    "isBCorp": false,
    "isCurrentSession": false,
    "social": {
      "linkedin": "",
      "twitter": "",
      "facebook": "",
      "crunchbase": ""
    },
    "extra": {}
  },
  {
    "source": "yc",
    "name": "Optifye.ai",
    "description": "AI performance monitoring for factory workers",
    "logo": "https://bookface-images.s3.amazonaws.com/small_logos/d86ffdce2296389239f29bc23023bc7867815208.png",
    "website": "https://www.optifye.ai",
    "location": "San Francisco, CA, USA",
    "region": "United States of America",
    "subregion": "",
    "tags": [
      "Hard Tech",
      "Computer Vision",
      "Manufacturing"
    ],
    "year": 2025,
    "program": "YC Winter 2025",
    "programSlugs": [
      "yc-winter-2025"
    ],
    "isExit": false,
    "isUnicorn": false,
    "isBCorp": false,
    "isCurrentSession": false,
    "social": {
      "linkedin": "",
      "twitter": "",
      "facebook": "",
      "crunchbase": ""
    },
    "extra": {}
  },
  {
    "source": "yc",
    "name": "Permitify",
    "description": "AI co-pilot for building plan review and building code compliance",
    "logo": "https://bookface-images.s3.amazonaws.com/small_logos/e0fb1e449f45c8f9ca33c6947992cac6af3e8c0f.png",
    "website": "https://permitify.com",
    "location": "",
    "region": "Unspecified",
    "subregion": "",
    "tags": [
      "Real Estate and Construction",
      "Construction",
      "Generative AI",
      "GovTech",
      "Computer Vision"
    ],
    "year": 2025,
    "program": "YC Winter 2025",
    "programSlugs": [
      "yc-winter-2025"
    ],
    "isExit": false,
    "isUnicorn": false,
    "isBCorp": false,
    "isCurrentSession": false,
    "social": {
      "linkedin": "",
      "twitter": "",
      "facebook": "",
      "crunchbase": ""
    },
    "extra": {}
  },
  {
    "source": "yc",
    "name": "Kirana AI",
    "description": "AI manager for physical stores",
    "logo": "https://bookface-images.s3.amazonaws.com/small_logos/6bc9cf5c0f4cd5c6141c30f400757b42039051c6.png",
    "website": "https://www.kirana-ai.com",
    "location": "New York, NY, USA",
    "region": "United States of America",
    "subregion": "",
    "tags": [
      "Retail",
      "Grocery",
      "Computer Vision",
      "AI"
    ],
    "year": 2025,
    "program": "YC Spring 2025",
    "programSlugs": [
      "yc-spring-2025"
    ],
    "isExit": false,
    "isUnicorn": false,
    "isBCorp": false,
    "isCurrentSession": false,
    "social": {
      "linkedin": "",
      "twitter": "",
      "facebook": "",
      "crunchbase": ""
    },
    "extra": {}
  },
  {
    "source": "yc",
    "name": "Code Four",
    "description": "Modernizing the police workflow.",
    "logo": "https://bookface-images.s3.amazonaws.com/small_logos/484fe167f81b504f3783e0d04f12060ec5bf7d11.png",
    "website": "https://codefour.us/",
    "location": "San Francisco, CA, USA",
    "region": "United States of America",
    "subregion": "",
    "tags": [
      "Government",
      "Artificial Intelligence",
      "GovTech",
      "Computer Vision"
    ],
    "year": 2025,
    "program": "YC Spring 2025",
    "programSlugs": [
      "yc-spring-2025"
    ],
    "isExit": false,
    "isUnicorn": false,
    "isBCorp": false,
    "isCurrentSession": false,
    "social": {
      "linkedin": "",
      "twitter": "",
      "facebook": "",
      "crunchbase": ""
    },
    "extra": {}
  },
  {
    "source": "yc",
    "name": "Bidflow",
    "description": "AI Takeoffs for Electrical",
    "logo": "https://bookface-images.s3.amazonaws.com/small_logos/fb5bdff2af780675e7950b4a0fb5dcad2dfdc802.png",
    "website": "https://usebidflow.com",
    "location": "New York, NY, USA",
    "region": "United States of America",
    "subregion": "",
    "tags": [
      "Real Estate and Construction",
      "Construction",
      "SaaS",
      "Computer Vision",
      "Infrastructure"
    ],
    "year": 2026,
    "program": "YC Winter 2026",
    "programSlugs": [
      "yc-winter-2026"
    ],
    "isExit": false,
    "isUnicorn": false,
    "isBCorp": false,
    "isCurrentSession": false,
    "social": {
      "linkedin": "",
      "twitter": "",
      "facebook": "",
      "crunchbase": ""
    },
    "extra": {}
  },
  {
    "source": "yc",
    "name": "OnDeck AI",
    "description": "Analyze any footage, without training a model",
    "logo": "https://bookface-images.s3.amazonaws.com/small_logos/9fb6ad4cbd4cdfac49ff1b40404d7053d5789883.png",
    "website": "https://www.ondeckai.com",
    "location": "Vancouver, BC, Canada",
    "region": "Canada",
    "subregion": "",
    "tags": [
      "Analytics",
      "Machine Learning",
      "SaaS",
      "Computer Vision",
      "Video"
    ],
    "year": 2025,
    "program": "YC Summer 2025",
    "programSlugs": [
      "yc-summer-2025"
    ],
    "isExit": false,
    "isUnicorn": false,
    "isBCorp": false,
    "isCurrentSession": false,
    "social": {
      "linkedin": "",
      "twitter": "",
      "facebook": "",
      "crunchbase": ""
    },
    "extra": {}
  },
  {
    "source": "yc",
    "name": "Rebulk",
    "description": "Accurately measure and monitor bulk inventory",
    "logo": "https://bookface-images.s3.amazonaws.com/small_logos/37f1f3fac3b53d55834007e8aa34e2f8bb7a1198.png",
    "website": "https://www.rebulk.com",
    "location": "Olathe, KS, USA",
    "region": "United States of America",
    "subregion": "",
    "tags": [
      "Supply Chain and Logistics",
      "Computer Vision",
      "Supply Chain",
      "Agriculture",
      "AI",
      "Industrial"
    ],
    "year": 2025,
    "program": "YC Summer 2025",
    "programSlugs": [
      "yc-summer-2025"
    ],
    "isExit": false,
    "isUnicorn": false,
    "isBCorp": false,
    "isCurrentSession": false,
    "social": {
      "linkedin": "",
      "twitter": "",
      "facebook": "",
      "crunchbase": ""
    },
    "extra": {}
  },
  {
    "source": "yc",
    "name": "Efference",
    "description": "",
    "logo": "https://bookface-images.s3.amazonaws.com/small_logos/54d1482241918ee48c1c994945fd8c443280d29b.png",
    "website": "https://efference.ai",
    "location": "San Francisco, CA, USA",
    "region": "United States of America",
    "subregion": "",
    "tags": [
      "Industrials",
      "Manufacturing and Robotics",
      "Robotics",
      "Computer Vision"
    ],
    "year": 2025,
    "program": "YC Fall 2025",
    "programSlugs": [
      "yc-fall-2025"
    ],
    "isExit": false,
    "isUnicorn": false,
    "isBCorp": false,
    "isCurrentSession": false,
    "social": {
      "linkedin": "",
      "twitter": "",
      "facebook": "",
      "crunchbase": ""
    },
    "extra": {}
  },
  {
    "source": "yc",
    "name": "Structured AI",
    "description": "AI workforce for Construction Engineering",
    "logo": "https://bookface-images.s3.amazonaws.com/small_logos/7b994637fa890bb7d41d69d022b3d15f6e4f3e8c.png",
    "website": "https://www.getstructured.ai/",
    "location": "New York, NY, USA",
    "region": "United States of America",
    "subregion": "",
    "tags": [
      "Real Estate and Construction",
      "Construction",
      "Computer Vision",
      "Architecture",
      "AI"
    ],
    "year": 2025,
    "program": "YC Fall 2025",
    "programSlugs": [
      "yc-fall-2025"
    ],
    "isExit": false,
    "isUnicorn": false,
    "isBCorp": false,
    "isCurrentSession": false,
    "social": {
      "linkedin": "",
      "twitter": "",
      "facebook": "",
      "crunchbase": ""
    },
    "extra": {}
  },
  {
    "source": "yc",
    "name": "Allus AI",
    "description": "Transforming manufacturing with our next-gen Vision Foundation Model",
    "logo": "https://bookface-images.s3.amazonaws.com/small_logos/e556d72ba8162e6d77731f52ccea802c98b54fa3.png",
    "website": "https://allus.ai",
    "location": "Atlanta, GA, USA",
    "region": "United States of America",
    "subregion": "",
    "tags": [
      "Industrials",
      "Manufacturing and Robotics",
      "Artificial Intelligence",
      "Machine Learning",
      "SaaS",
      "Computer Vision",
      "Manufacturing"
    ],
    "year": 2025,
    "program": "YC Fall 2025",
    "programSlugs": [
      "yc-fall-2025"
    ],
    "isExit": false,
    "isUnicorn": false,
    "isBCorp": false,
    "isCurrentSession": false,
    "social": {
      "linkedin": "",
      "twitter": "",
      "facebook": "",
      "crunchbase": ""
    },
    "extra": {}
  },
  {
    "source": "yc",
    "name": "Kita",
    "description": "Automate credit review for lenders in emerging markets",
    "logo": "https://bookface-images.s3.amazonaws.com/small_logos/0e2c404c5bbc49c9c8e25d9c60779b50f507ba65.png",
    "website": "https://www.usekita.com/",
    "location": "San Francisco, CA, USA",
    "region": "United States of America",
    "subregion": "",
    "tags": [
      "Fintech",
      "Computer Vision",
      "Lending",
      "Emerging Markets"
    ],
    "year": 2026,
    "program": "YC Winter 2026",
    "programSlugs": [
      "yc-winter-2026"
    ],
    "isExit": false,
    "isUnicorn": false,
    "isBCorp": false,
    "isCurrentSession": false,
    "social": {
      "linkedin": "",
      "twitter": "",
      "facebook": "",
      "crunchbase": ""
    },
    "extra": {}
  },
  {
    "source": "yc",
    "name": "GrazeMate",
    "description": "Robot Cowboys that Herd Cattle with AI Drones",
    "logo": "https://bookface-images.s3.amazonaws.com/small_logos/d2a4475db614107fb0effa347e625a6885ca8045.png",
    "website": "https://grazemate.com",
    "location": "Sydney, NSW, Australia",
    "region": "Australia",
    "subregion": "",
    "tags": [
      "Industrials",
      "Agriculture",
      "Reinforcement Learning",
      "Drones",
      "Computer Vision"
    ],
    "year": 2026,
    "program": "YC Winter 2026",
    "programSlugs": [
      "yc-winter-2026"
    ],
    "isExit": false,
    "isUnicorn": false,
    "isBCorp": false,
    "isCurrentSession": false,
    "social": {
      "linkedin": "",
      "twitter": "",
      "facebook": "",
      "crunchbase": ""
    },
    "extra": {}
  }
]