[
  {
    "source": "antler",
    "name": "Buyo",
    "description": "Buyo",
    "logo": "https://cdn.prod.website-files.com/68d622fc073c7e5dead1105e/695ee26d06281e10a460fcc2_portfolio%252Fcompany%252F61784255-bdd9-4c13-9fa1-e237d7b5a037%252F1725422209838-logo.avif",
    "website": "https://www.buyoplastic.com/",
    "location": "We upcycle discarded biowaste and convert them into a nature-based and fully biodegradable bio-material to replace traditional plastics.",
    "region": "",
    "subregion": "",
    "tags": [
      "Vietnam\nEnergy and ClimateTech\n2022",
      "Vietnam",
      "Energy and ClimateTech",
      "2022"
    ],
    "year": "",
    "program": "Antler",
    "programSlugs": [
      "antler"
    ],
    "isExit": false,
    "isUnicorn": false,
    "isBCorp": false,
    "isCurrentSession": false,
    "social": {
      "linkedin": "",
      "twitter": "",
      "facebook": "",
      "crunchbase": ""
    },
    "extra": {
      "name": "Buyo",
      "description": "Buyo",
      "location": "We upcycle discarded biowaste and convert them into a nature-based and fully biodegradable bio-material to replace traditional plastics.",
      "tags": [
        "Vietnam\nEnergy and ClimateTech\n2022",
        "Vietnam",
        "Vietnam",
        "Energy and ClimateTech",
        "Energy and ClimateTech",
        "2022",
        "2022"
      ],
      "logo": "https://cdn.prod.website-files.com/68d622fc073c7e5dead1105e/695ee26d06281e10a460fcc2_portfolio%252Fcompany%252F61784255-bdd9-4c13-9fa1-e237d7b5a037%252F1725422209838-logo.avif",
      "website": "https://www.buyoplastic.com/"
    }
  }
]